django_athm/__init__.py
django_athm/admin.py
django_athm/apps.py
django_athm/conf.py
django_athm/constants.py
django_athm/models.py
django_athm/signals.py
django_athm/urls.py
django_athm/utils.py
django_athm/views.py
django_athm/locale/en/LC_MESSAGES/django.po
django_athm/locale/es/LC_MESSAGES/django.po
django_athm/management/__init__.py
django_athm/management/commands/__init__.py
django_athm/management/commands/athm_sync.py
django_athm/management/commands/install_webhook.py
django_athm/migrations/0001_initial.py
django_athm/migrations/0002_allow_null_reference_number.py
django_athm/migrations/__init__.py
django_athm/services/__init__.py
django_athm/services/client_service.py
django_athm/services/payment_service.py
django_athm/services/webhook_processor.py
django_athm/templates/admin/django_athm/payment/refund_confirmation.html
django_athm/templates/admin/django_athm/webhookevent/change_list.html
django_athm/templates/admin/django_athm/webhookevent/install_webhooks.html
django_athm/templates/admin/django_athm/webhookevent/reprocess_confirmation.html
django_athm/templates/django_athm/button.html
django_athm/templatetags/__init__.py
django_athm/templatetags/django_athm.py
django_athm-1.0.1.dist-info/METADATA
django_athm-1.0.1.dist-info/WHEEL
django_athm-1.0.1.dist-info/licenses/LICENSE
django_athm-1.0.1.dist-info/RECORD
