Metadata-Version: 2.4
Name: django-athm
Version: 1.0.1
Summary: Django + ATH Móvil
Project-URL: Homepage, https://github.com/django-athm/django-athm
Project-URL: Repository, https://github.com/django-athm/django-athm
Project-URL: Documentation, https://django-athm.readthedocs.io
Project-URL: Issues, https://github.com/django-athm/django-athm/issues
Author-email: Raúl Negrón-Otero <raul@rnosoftware.com>
Maintainer-email: Raúl Negrón-Otero <raul@rnosoftware.com>
License: MIT
License-File: LICENSE
Keywords: ATH Móvil,Django,athm,payments
Classifier: Development Status :: 5 - Production/Stable
Classifier: Environment :: Web Environment
Classifier: Framework :: Django
Classifier: Framework :: Django :: 5.1
Classifier: Framework :: Django :: 5.2
Classifier: Framework :: Django :: 6.0
Classifier: Intended Audience :: Developers
Classifier: License :: OSI Approved :: MIT License
Classifier: Programming Language :: Python :: 3
Classifier: Programming Language :: Python :: 3.10
Classifier: Programming Language :: Python :: 3.11
Classifier: Programming Language :: Python :: 3.12
Classifier: Programming Language :: Python :: 3.13
Classifier: Programming Language :: Python :: 3.14
Classifier: Topic :: Office/Business :: Financial
Requires-Python: >=3.10
Requires-Dist: athm~=0.4.1
